levatas_alira_cli/__init__.py
levatas_alira_cli/alr.py
levatas_alira_cli/diagnostics.py
tests/__init__.py
tests/test_cli.py
tests/test_diagnostics.py
levatas_alira_cli-0.0.47.dist-info/METADATA
levatas_alira_cli-0.0.47.dist-info/WHEEL
levatas_alira_cli-0.0.47.dist-info/entry_points.txt
levatas_alira_cli-0.0.47.dist-info/top_level.txt
levatas_alira_cli-0.0.47.dist-info/RECORD
