Metadata-Version: 2.1
Name: levatas-alira-cli
Version: 0.0.47
Summary: Alira CLI
Home-page: https://github.com/vinsa-ai/alira-cli
Author: Levatas
Author-email: svpino@gmail.com
License: UNKNOWN
Platform: UNKNOWN
Requires-Dist: Click
Requires-Dist: Docker
Requires-Dist: python-dateutil
Requires-Dist: cryptography (>=36.0.1)
Requires-Dist: pyyaml
Requires-Dist: levatas-alira-licensing
